.DS_Store
dc_connector/__init__.py
dc_connector/connector.py
dc_connector/crypt.py
dc_connector/destination.py
dc_connector/source.py
dc_connector_templates-0.2.31.dist-info/METADATA
dc_connector_templates-0.2.31.dist-info/WHEEL
dc_connector_templates-0.2.31.dist-info/top_level.txt
dc_connector_templates-0.2.31.dist-info/RECORD
