Metadata-Version: 2.1
Name: dc-connector-templates
Version: 0.2.31
Summary: Connector Templates for data connector.
Home-page: UNKNOWN
Author: joshatxantie
License: MIT
Platform: UNKNOWN
Requires-Python: >=3.6
Requires-Dist: boto3 (==1.20.24)
Requires-Dist: botocore (==1.23.24)
Requires-Dist: jmespath (==0.10.0)
Requires-Dist: requests (==2.27.1)
Requires-Dist: numpy (==1.21.4)
Requires-Dist: pandas (==1.3.5)
Requires-Dist: pycryptodome (==3.12.0)
Requires-Dist: pyodbc (==4.0.32)
Requires-Dist: python-dateutil (==2.8.2)
Requires-Dist: python-dotenv (==0.19.2)
Requires-Dist: pytz (==2021.3)
Requires-Dist: PyYAML (==6.0)
Requires-Dist: s3transfer (==0.5.0)
Requires-Dist: six (==1.16.0)
Requires-Dist: urllib3 (==1.26.7)
